tissueloc/__init__.py
tissueloc/load_slide.py
tissueloc/locate_tissue.py
tissueloc/setup.py
tissueloc-2.1.0.dist-info/AUTHORS.md
tissueloc-2.1.0.dist-info/LICENSE
tissueloc-2.1.0.dist-info/METADATA
tissueloc-2.1.0.dist-info/WHEEL
tissueloc-2.1.0.dist-info/top_level.txt
tissueloc-2.1.0.dist-info/RECORD
