Metadata-Version: 2.1
Name: tissueloc
Version: 2.1.0
Summary: Localize the tissue regions in whole slide pathology images.
Home-page: https://github.com/PingjunChen/TissueLocalizer
Author: Pingjun Chen
Author-email: chenpingjun@gmx.com
License: MIT
Platform: UNKNOWN
Classifier: Development Status :: 4 - Beta
Classifier: Intended Audience :: Developers
Classifier: Intended Audience :: Science/Research
Classifier: License :: OSI Approved :: MIT License
Classifier: Programming Language :: Python
Classifier: Programming Language :: Python :: 3
Classifier: Programming Language :: Python :: 3.6
Classifier: Topic :: Scientific/Engineering
Requires-Dist: numpy (>=1.16.2)
Requires-Dist: scikit-image (>=0.14.2)
Requires-Dist: Pillow (>=6.2.0)
Requires-Dist: opencv-python (>=4.1.2.30)
Requires-Dist: openslide-python (>=1.1.1)
